Workbook
Name ctl_scenario: Sensitivity!$E$5
Name ctl_tornado: Sensitivity!$E$6
Name ctl_ovr_1: Sensitivity!$E$7
Name ctl_ovr_2: Sensitivity!$E$8
Name ctl_ovr_3: Sensitivity!$E$9
Name ctl_ovr_4: Sensitivity!$E$10

Sheet Cover
B2: Example Co - three-pillar impact model (TEMPLATE: replace every input)
B4: Company | C4: Example Co (illustrative)
B5: Currency / units | C5: EURm
B6: Timeline | C6: 2020-2024 actuals, 2025-2029 projection
B7: Objective | C7: revenue growth
B8: Prepared by | C8: Team name
B9: As of | C9: 2026-01-01
B11: How to read | C11: Inputs -> Calculations -> Outputs / Bridge / Sensitivity; Checks must show 0 errors.
B12: Colours | C12: Blue on yellow = typed input (Inputs, Actuals). Orange = Sensitivity control. Green = headline output. Everything else is a formula.
B13: Grades | C13: Source reliability A (reliable) - F (cannot judge); information credibility 1 (confirmed) - 6 (cannot judge). Every input carries one.
B14: Scenarios | C14: Low/Base/High move every ranged input to its pessimistic/optimistic end (polarity aware).
B15: Recalculate | C15: Excel recalculates on open. Data Tables: Formulas > Calculation Options > Automatic.
B16: Independent check | C16: python scripts/check_model.py <this file> (must pass every check)
B17: History | C17: 3 reported series on Actuals; growth, CAGR, quartiles and margins in Calculations section 0. 2 inputs take their value from history (cust0, cust_g). Baseline growth is checked against the historical band (Checks).
B19: Headline: the case objectives in 2029 (base case = do nothing)
B20: KPI | C20: Base case | D20: With strategies | E20: Change | F20: Better?
B21: Revenue (EURm) | C21: =Objectives!E5 | D21: =Objectives!F5 | E21: =Objectives!G5 | F21: =Objectives!J5
B22: EBITDA (EURm) | C22: =Objectives!E6 | D22: =Objectives!F6 | E22: =Objectives!G6 | F22: =Objectives!J6
B23: EBITDA margin (pp) | C23: =Objectives!E7 | D23: =Objectives!F7 | E23: =Objectives!G7 | F23: =Objectives!J7
B24: Valuation (secondary) | C24: =Calculations!$E$172 | D24: NPV in EURm; see Outputs. Breakdown through the consulting frameworks: Frameworks sheet.

Sheet Objectives
B1: Case objectives - how the strategies move them
B2: Base case = do nothing. Change = with strategies minus base case, in 2029 and summed over 2025-2029. All cells link to Calculations section 10.
B4: Objective | C4: KPI | D4: Unit | E4: Base case 2029 | F4: With strategies 2029 | G4: Change 2029 | H4: Change % | I4: Cumulative change 2025-2029 | J4: Better?
B5: Profit: Revenue growth | C5: Revenue | D5: EURm | E5: =Calculations!$E$209 | F5: =Calculations!$E$210 | G5: =Calculations!$E$211 | H5: =IF(E5=0,"n/a",G5/ABS(E5)) | I5: =Calculations!$E$212 | J5: =IF(G5=0,"no change",IF(G5>0,"better","worse"))
B6: Profit: Profitability | C6: EBITDA | D6: EURm | E6: =Calculations!$E$213 | F6: =Calculations!$E$214 | G6: =Calculations!$E$215 | H6: =IF(E6=0,"n/a",G6/ABS(E6)) | I6: =Calculations!$E$216 | J6: =IF(G6=0,"no change",IF(G6>0,"better","worse"))
B7: Profit: Profitability | C7: EBITDA margin | D7: pp | E7: =Calculations!$E$217 | F7: =Calculations!$E$218 | G7: =Calculations!$E$219 | J7: =IF(G7=0,"no change",IF(G7>0,"better","worse"))
B9: Contribution of each strategy to the change in 2029 (vs base case)
B10: Pillar | C10: Strategy | D10: Revenue (EURm) | E10: EBITDA (EURm)
B11: Pillar A | C11: Initiative A1 | D11: =Calculations!P125 | E11: =Calculations!P149
B12: Pillar B | C12: Initiative B1 | D12: =Calculations!P126 | E12: =Calculations!P150
B13: Pillar C | C13: Initiative C1 | D13: =Calculations!P127 | E13: =Calculations!P151
B14: Total | D14: =SUM(D11:D13) | E14: =SUM(E11:E13)
B16: By pillar (change in 2029 vs base case)
B17: Pillar | D17: Revenue (EURm) | E17: EBITDA (EURm)
B18: Pillar A | D18: =D11 | E18: =E11
B19: Pillar B | D19: =D12 | E19: =E12
B20: Pillar C | D20: =D13 | E20: =E13
B21: Total | D21: =SUM(D18:D20) | E21: =SUM(E18:E20)

Sheet Frameworks
B1: The impact through the consulting frameworks
B2: Each view splits the same change vs the base case (2029; revenue summed over 2025-2029); every view adds up to the strategy total (Checks).
B4: 1. Triple bottom line (Elkington): profit, planet and people by pillar
B5: Rows are the team's pillars; columns are the case objectives.
B6: Category | C6: Cumulative incremental revenue (EURm) | D6: Profit: Revenue 2029 (EURm) | E6: Profit: EBITDA 2029 (EURm) | F6: Strategies
B7: Pillar A | C7: =SUM(Calculations!L125:P125) | D7: =Calculations!P125 | E7: =Calculations!P149 | F7: Initiative A1
B8: Pillar B | C8: =SUM(Calculations!L126:P126) | D8: =Calculations!P126 | E8: =Calculations!P150 | F8: Initiative B1
B9: Pillar C | C9: =SUM(Calculations!L127:P127) | D9: =Calculations!P127 | E9: =Calculations!P151 | F9: Initiative C1
B10: Total | C10: =SUM(C7:C9) | D10: =SUM(D7:D9) | E10: =SUM(E7:E9)
B13: 2. Profitability tree: where the change in EBITDA comes from (2029)
B14: Profit = (volume x price) x margin - costs. Each strategy's effect, split by the lever it pulls.
B15: Lever | C15: EBITDA change 2029 (EURm) | D15: Strategies
B16: Revenue: more volume (customers, visits, occupancy), after variable costs | C16: =Calculations!P125*Calculations!$E$49+Calculations!P126*Calculations!$E$49 | D16: Initiative A1, Initiative B1
B17: Revenue: higher price or spend per unit, after variable costs | C17: =Calculations!P127*Calculations!$E$49 | D17: Initiative C1
B18: Revenue: new streams (volume x price of a new offer), after variable costs | C18: =0 | D18: -
B19: Cost: savings (cost avoided) | C19: =0 | D19: -
B20: Cost: operating cost added by the strategies | C20: =-Calculations!P137-Calculations!P138 | D20: Initiative A1, Initiative C1
B21: Total | C21: =SUM(C16:C20)
B24: 3. Ansoff matrix: growth vector
B25: Where the growth comes from: existing or new products and markets; efficiency moves cost, not growth.
B26: Category | C26: Cumulative incremental revenue (EURm) | D26: Profit: Revenue 2029 (EURm) | E26: Profit: EBITDA 2029 (EURm) | F26: Strategies
B27: Existing products, existing markets (selling more into today's market) | C27: =SUM(Calculations!L125:P125)+SUM(Calculations!L126:P126)+SUM(Calculations!L127:P127) | D27: =Calculations!P125+Calculations!P126+Calculations!P127 | E27: =Calculations!P149+Calculations!P150+Calculations!P151 | F27: Initiative A1, Initiative B1, Initiative C1
B28: New products, existing markets (product development) | C28: =0 | D28: =0 | E28: =0 | F28: -
B29: Existing products, new markets (market development) | C29: =0 | D29: =0 | E29: =0 | F29: -
B30: New products, new markets (diversification) | C30: =0 | D30: =0 | E30: =0 | F30: -
B31: Efficiency (cost and resources) | C31: =0 | D31: =0 | E31: =0 | F31: -
B32: Total | C32: =SUM(C27:C31) | D32: =SUM(D27:D31) | E32: =SUM(E27:E31)
B35: 4. Marketing mix (4Ps)
B36: Which marketing lever each strategy pulls.
B37: Category | C37: Cumulative incremental revenue (EURm) | D37: Profit: Revenue 2029 (EURm) | E37: Profit: EBITDA 2029 (EURm) | F37: Strategies
B38: Price | C38: =SUM(Calculations!L127:P127) | D38: =Calculations!P127 | E38: =Calculations!P151 | F38: Initiative C1
B39: Product | C39: =0 | D39: =0 | E39: =0 | F39: -
B40: Place (channel) | C40: =0 | D40: =0 | E40: =0 | F40: -
B41: Promotion | C41: =0 | D41: =0 | E41: =0 | F41: -
B42: Not a marketing-mix lever (cost, operations) | C42: =0 | D42: =0 | E42: =0 | F42: -
B43: Not tagged (set frameworks.<lens> on the initiative) | C43: =SUM(Calculations!L125:P125)+SUM(Calculations!L126:P126) | D43: =Calculations!P125+Calculations!P126 | E43: =Calculations!P149+Calculations!P150 | F43: Initiative A1, Initiative B1
B44: Total | C44: =SUM(C38:C43) | D44: =SUM(D38:D43) | E44: =SUM(E38:E43)
B47: 5. Value chain (Porter)
B48: Which activity of the business each strategy changes.
B49: Category | C49: Cumulative incremental revenue (EURm) | D49: Profit: Revenue 2029 (EURm) | E49: Profit: EBITDA 2029 (EURm) | F49: Strategies
B50: Inbound logistics | C50: =0 | D50: =0 | E50: =0 | F50: -
B51: Operations | C51: =0 | D51: =0 | E51: =0 | F51: -
B52: Outbound logistics | C52: =0 | D52: =0 | E52: =0 | F52: -
B53: Marketing & sales | C53: =0 | D53: =0 | E53: =0 | F53: -
B54: Service | C54: =0 | D54: =0 | E54: =0 | F54: -
B55: Procurement | C55: =0 | D55: =0 | E55: =0 | F55: -
B56: Technology development | C56: =0 | D56: =0 | E56: =0 | F56: -
B57: Human resource management | C57: =0 | D57: =0 | E57: =0 | F57: -
B58: Firm infrastructure | C58: =0 | D58: =0 | E58: =0 | F58: -
B59: Not tagged (set frameworks.<lens> on the initiative) | C59: =SUM(Calculations!L125:P125)+SUM(Calculations!L126:P126)+SUM(Calculations!L127:P127) | D59: =Calculations!P125+Calculations!P126+Calculations!P127 | E59: =Calculations!P149+Calculations!P150+Calculations!P151 | F59: Initiative A1, Initiative B1, Initiative C1
B60: Total | C60: =SUM(C50:C59) | D60: =SUM(D50:D59) | E60: =SUM(E50:E59)
B63: 6. Balanced scorecard: outcomes, customers, processes, enablers
B64: Kaplan & Norton's four perspectives; the financial perspective widened to the case objectives.
B65: Perspective | C65: Measure | D65: Value | E65: Unit
B66: Outcomes (case objectives) | C66: Revenue: change in 2029 vs base case | D66: =Calculations!$E$211 | E66: EURm
B67: Outcomes (case objectives) | C67: EBITDA: change in 2029 vs base case | D67: =Calculations!$E$215 | E67: EURm
B68: Outcomes (case objectives) | C68: EBITDA margin: change in 2029 vs base case | D68: =Calculations!$E$219 | E68: pp
B69: Outcomes (case objectives) | C69: Valuation: NPV of the strategies | D69: =Calculations!$E$172 | E69: EURm
B70: Customers | C70: Revenue from more customers or use, 2025-2029 | D70: =SUM(Calculations!L125:P125)+SUM(Calculations!L126:P126) | E70: EURm
B71: Customers | C71: Revenue from new offers, 2025-2029 | D71: =0 | E71: EURm
B72: Internal processes | C72: Cost savings, 2025-2029 | D72: =0 | E72: EURm
B73: Learning & growth (enablers) | C73: Capex invested, 2025-2029 | D73: =SUM(Calculations!L142:P142) | E73: EURm
B74: Learning & growth (enablers) | C74: Operating cost of running the strategies, 2025-2029 | D74: =SUM(Calculations!L139:P139) | E74: EURm

Sheet Inputs
B1: Inputs - assumptions register
B2: Every number used by the model, once. Blue = typed input. Grade: source reliability A-F, information credibility 1-6 (A1 best).
A5: ID | B5: Input | C5: Unit | D5: Type | E5: Low | F5: Base | G5: High | H5: Polarity | I5: Source | J5: Date | K5: Link / database path | L5: Grade | M5: Benchmark low (p25) | N5: Benchmark median | O5: Benchmark high (p75) | P5: Benchmark source | Q5: Justification (if above p75) | R5: Used by | S5: Key | T5: Revision
B6: Baseline drivers
A7: 1 | B7: Customers, base year | C7: m | D7: actual | E7: =Actuals!$K$8 | F7: =Actuals!$K$8 | G7: =Actuals!$K$8 | H7: 1 | I7: History: last reported value of Customers (reported) 2020-2024 (live link to the Actuals sheet). Data: ILLUSTRATIVE - replace (annual report KPIs / case pack) | J7: 2026-01-01 | K7: - | L7: F6 | R7: leaf customers | S7: cust0
A8: 2 | B8: Baseline growth in customers | C8: % | D8: assumption | E8: 0 | F8: =Calculations!$E$25 | G8: 0.02 | H8: 1 | I8: History: CAGR of Customers (reported) 2020-2024 (live link to the Actuals sheet). Data: ILLUSTRATIVE - replace (annual report KPIs / case pack) | J8: 2026-01-01 | K8: - | L8: F6 | R8: leaf customers | S8: cust_g
A9: 3 | B9: Purchases per customer per year | C9: x | D9: actual | E9: 8 | F9: 8 | G9: 8 | H9: 1 | I9: ILLUSTRATIVE - replace (loyalty data) | J9: 2026-01-01 | K9: - | L9: F6 | R9: leaf freq | S9: freq0
A10: 4 | B10: Average ticket, base year | C10: EUR | D10: actual | E10: 25 | F10: 25 | G10: 25 | H10: 1 | I10: Derived: revenue / (customers x purchases) | J10: 2026-01-01 | K10: - | L10: F6 | R10: leaf ticket | S10: ticket0
A11: 5 | B11: Price inflation | C11: % | D11: assumption | E11: 0.015 | F11: 0.02 | G11: 0.03 | H11: 1 | I11: ILLUSTRATIVE - replace (IMF WEO PCPIPCH) | J11: 2026-01-01 | K11: - | L11: F6 | R11: leaf ticket | S11: infl
B12: Market ceilings
A13: 6 | B13: Ceiling: addressable customers | C13: m | D13: actual | E13: 4 | F13: 4 | G13: 4 | H13: 1 | I13: ILLUSTRATIVE - replace (national statistics office population in catchment) | J13: 2026-01-01 | K13: - | L13: F6 | R13: leaf customers | S13: market
A14: 7 | B14: Growth in addressable customers | C14: % | D14: assumption | E14: 0 | F14: 0.005 | G14: 0.01 | H14: 1 | I14: ILLUSTRATIVE - replace (Eurostat population projections) | J14: 2026-01-01 | K14: - | L14: F6 | R14: leaf customers | S14: market_g
B15: Revenue scaling
A16: 8 | B16: Unit conversion: EUR to EURm with customers in millions | C16: x | D16: conversion | E16: 1 | F16: 1 | G16: 1 | H16: 1 | I16: Arithmetic: m customers x purchases x EUR = EURm | J16: 2026-01-01 | K16: - | L16: A1 | S16: to_m
B17: Initiatives - Pillar A
A18: 9 | B18: Pillar A: peak uplift in customers | C18: % | D18: uplift | E18: 0.02 | F18: 0.04 | G18: 0.06 | H18: 1 | I18: ILLUSTRATIVE - replace | J18: 2026-01-01 | K18: - | L18: F6 | M18: 0.02 | N18: 0.04 | O18: 0.06 | P18: ILLUSTRATIVE - build the reference class (Factiva cases) (p25 / median / p75) | R18: a1 | S18: a_up
A19: 10 | B19: Annual erosion of initiative effects | C19: % | D19: assumption | E19: 0 | F19: 0.03 | G19: 0.06 | H19: 1 | I19: ILLUSTRATIVE - replace | J19: 2026-01-01 | K19: - | L19: F6 | R19: a1, b1, c1 | S19: decay
A20: 11 | B20: Bass p | C20: x | D20: assumption | E20: 0.02 | F20: 0.03 | G20: 0.06 | H20: 1 | I20: Sultan, Farley & Lehmann (1990) JMR: mean p = 0.03 (replace with analogous launch) | J20: 1990-02-01 | K20: JMR 27(1) | L20: B2 | R20: a1, b1 | S20: bass_p
A21: 12 | B21: Bass q | C21: x | D21: assumption | E21: 0.25 | F21: 0.38 | G21: 0.5 | H21: 1 | I21: Sultan, Farley & Lehmann (1990) JMR: mean q = 0.38 | J21: 1990-02-01 | K21: JMR 27(1) | L21: B2 | R21: a1, b1 | S21: bass_q
A22: 13 | B22: Launch year: Initiative A1 | C22: year | D22: plan | E22: 2025 | F22: 2025 | G22: 2025 | H22: 1 | I22: Team implementation plan | J22: 2026-01-01 | K22: Strategy deck / roadmap | L22: A1 | R22: a1 | S22: a1_launch
B23: Initiatives - Pillar B
A24: 14 | B24: Pillar B: peak uplift in purchase frequency | C24: % | D24: uplift | E24: 0.02 | F24: 0.03 | G24: 0.05 | H24: 1 | I24: ILLUSTRATIVE - replace | J24: 2026-01-01 | K24: - | L24: F6 | M24: 0.01 | N24: 0.03 | O24: 0.06 | P24: ILLUSTRATIVE - Scopus meta-analysis (p25 / median / p75) | R24: b1 | S24: b_up
A25: 15 | B25: Launch year: Initiative B1 | C25: year | D25: plan | E25: 2025 | F25: 2025 | G25: 2025 | H25: 1 | I25: Team implementation plan | J25: 2026-01-01 | K25: Strategy deck / roadmap | L25: A1 | R25: b1 | S25: b1_launch
B26: Initiatives - Pillar C
A27: 16 | B27: Pillar C: peak uplift in average ticket | C27: % | D27: uplift | E27: 0.01 | F27: 0.02 | G27: 0.04 | H27: 1 | I27: ILLUSTRATIVE - replace | J27: 2026-01-01 | K27: - | L27: F6 | M27: 0.01 | N27: 0.025 | O27: 0.05 | P27: ILLUSTRATIVE - Factiva / Euromonitor (p25 / median / p75) | R27: c1 | S27: c_up
A28: 17 | B28: Pillar C: years to full effect (linear ramp) | C28: years | D28: assumption | E28: 1 | F28: 2 | G28: 3 | H28: 1 | I28: ILLUSTRATIVE - replace (roll-out plan vs comparable launches) | J28: 2026-01-01 | K28: - | L28: F6 | R28: c1 | S28: c_ytp
A29: 18 | B29: Launch year: Initiative C1 | C29: year | D29: plan | E29: 2026 | F29: 2026 | G29: 2026 | H29: 1 | I29: Team implementation plan | J29: 2026-01-01 | K29: Strategy deck / roadmap | L29: A1 | R29: c1 | S29: c1_launch
B30: Costs
A31: 19 | B31: Pillar A: annual cost | C31: EURm | D31: cost | E31: 0.2 | F31: 0.3 | G31: 0.4 | H31: -1 | I31: ILLUSTRATIVE - replace | J31: 2026-01-01 | K31: - | L31: F6 | R31: a1 | S31: a_opex
A32: 20 | B32: Pillar B: launch investment | C32: EURm | D32: cost | E32: 0.5 | F32: 0.8 | G32: 1.2 | H32: -1 | I32: ILLUSTRATIVE - replace | J32: 2026-01-01 | K32: - | L32: F6 | R32: b1 | S32: b_capex
A33: 21 | B33: Pillar C: annual cost | C33: EURm | D33: cost | E33: 0.1 | F33: 0.2 | G33: 0.3 | H33: -1 | I33: ILLUSTRATIVE - replace | J33: 2026-01-01 | K33: - | L33: F6 | R33: c1 | S33: c_opex
B34: Finance & WACC
A35: 22 | B35: Contribution margin on incremental revenue | C35: % | D35: assumption | E35: 0.25 | F35: 0.35 | G35: 0.45 | H35: 1 | I35: ILLUSTRATIVE - replace ((revenue - variable costs) / revenue from the P&L) | J35: 2026-01-01 | K35: - | L35: F6 | R35: finance | S35: margin
A36: 23 | B36: Corporate tax rate | C36: % | D36: assumption | E36: 0.25 | F36: 0.25 | G36: 0.28 | H36: 1 | I36: ILLUSTRATIVE - replace (national tax law) | J36: 2026-01-01 | K36: - | L36: F6 | R36: finance | S36: tax
A37: 24 | B37: Risk-free rate | C37: % | D37: assumption | E37: 0.025 | F37: 0.03 | G37: 0.035 | H37: 1 | I37: ILLUSTRATIVE - replace (10y government yield, Bloomberg) | J37: 2026-01-01 | K37: - | L37: F6 | R37: finance | S37: rf
A38: 25 | B38: Levered beta | C38: x | D38: assumption | E38: 0.8 | F38: 1 | G38: 1.2 | H38: 1 | I38: ILLUSTRATIVE - replace (peer median, Bloomberg/WRDS) | J38: 2026-01-01 | K38: - | L38: F6 | R38: finance | S38: beta
A39: 26 | B39: Equity risk premium | C39: % | D39: assumption | E39: 0.04 | F39: 0.045 | G39: 0.05 | H39: 1 | I39: ILLUSTRATIVE - replace (Damodaran ctryprem) | J39: 2026-01-01 | K39: - | L39: F6 | R39: finance | S39: erp
A40: 27 | B40: Pre-tax cost of debt | C40: % | D40: assumption | E40: 0.04 | F40: 0.05 | G40: 0.06 | H40: 1 | I40: ILLUSTRATIVE - replace | J40: 2026-01-01 | K40: - | L40: F6 | R40: finance | S40: kd
A41: 28 | B41: Debt weight D/(D+E) | C41: % | D41: assumption | E41: 0.2 | F41: 0.3 | G41: 0.4 | H41: 1 | I41: ILLUSTRATIVE - replace | J41: 2026-01-01 | K41: - | L41: F6 | R41: finance | S41: wd
A42: 29 | B42: Terminal growth of incremental FCF after the horizon | C42: % | D42: assumption | E42: -0.05 | F42: -0.02 | G42: 0.01 | H42: 1 | I42: Modelling choice: effects fade 2%/yr after the horizon (low: 5% fade as competitors copy; high: +1%); Gordon growth model | J42: 2026-01-01 | K42: Damodaran, Investment Valuation (3rd ed.), ch. 12 | L42: C3 | R42: finance | S42: tv_g
A43: 30 | B43: Include terminal value (1 = yes, 0 = horizon only) | C43: switch | D43: control | E43: 1 | F43: 1 | G43: 1 | H43: 1 | I43: Modelling choice (horizon-only NPV is also reported) | J43: 2026-01-01 | K43: Outputs: headline results | L43: A1 | R43: finance | S43: tv_on
B44: Model settings
A45: 31 | B45: First historical year shown | C45: year | D45: constant | E45: 2020 | F45: 2020 | G45: 2020 | H45: 1 | I45: Modelling convention (this model) | J45: 2026-01-01 | K45: Cover sheet | L45: A1 | S45: first_hist_year
A46: 32 | B46: Base year (last reported actuals) | C46: year | D46: constant | E46: 2024 | F46: 2024 | G46: 2024 | H46: 1 | I46: Modelling convention (this model) | J46: 2026-01-01 | K46: Cover sheet | L46: A1 | S46: base_year
A47: 33 | B47: Growth cap: max YoY growth of target revenue | C47: % | D47: constant | E47: 0.25 | F47: 0.25 | G47: 0.25 | H47: 1 | I47: Modelling convention (this model) | J47: 2026-01-01 | K47: Cover sheet | L47: A1 | S47: growth_cap
A48: 34 | B48: Tolerance: baseline vs reported revenue | C48: % | D48: constant | E48: 0.02 | F48: 0.02 | G48: 0.02 | H48: 1 | I48: Modelling convention (this model) | J48: 2026-01-01 | K48: Cover sheet | L48: A1 | S48: calib_tol
A49: 35 | B49: Tolerance: totals vs sum of parts | C49: abs | D49: constant | E49: 1e-06 | F49: 1e-06 | G49: 1e-06 | H49: 1 | I49: Modelling convention (this model) | J49: 2026-01-01 | K49: Cover sheet | L49: A1 | S49: sum_tol
A50: 36 | B50: Tornado tie-break step (keeps ranks unique when two swings are equal) | C50: abs | D50: constant | E50: 1e-09 | F50: 1e-09 | G50: 1e-09 | H50: 1 | I50: Modelling convention (this model) | J50: 2026-01-01 | K50: Cover sheet | L50: A1 | S50: tie_step
A51: 37 | B51: History band: lower percentile of YoY growth | C51: % | D51: constant | E51: 0.25 | F51: 0.25 | G51: 0.25 | H51: 1 | I51: Modelling convention (this model) | J51: 2026-01-01 | K51: Cover sheet | L51: A1 | S51: hist_p_low
A52: 38 | B52: History band: upper percentile of YoY growth | C52: % | D52: constant | E52: 0.75 | F52: 0.75 | G52: 0.75 | H52: 1 | I52: Modelling convention (this model) | J52: 2026-01-01 | K52: Cover sheet | L52: A1 | S52: hist_p_high
A53: 39 | B53: History band: tolerance around the band (baseline growth vs history) | C53: % | D53: constant | E53: 0.01 | F53: 0.01 | G53: 0.01 | H53: 1 | I53: Modelling convention (this model) | J53: 2026-01-01 | K53: Cover sheet | L53: A1 | S53: hist_tol

Sheet Actuals
B1: Actuals - reported financials
B2: Base year comes from reported accounts, never a press summary.
A5: ID | B5: Item | C5: Unit | D5: Source | E5: Grade | F5: Date | G5: =Calculations!G3 | H5: =Calculations!H3 | I5: =Calculations!I3 | J5: =Calculations!J3 | K5: =Calculations!K3 | L5: =Calculations!L3 | M5: =Calculations!M3 | N5: =Calculations!N3 | ... P5: =Calculations!P3
A6: rev | B6: Revenue (reported) | C6: EURm | D6: ILLUSTRATIVE - replace with SABI/Orbis or the annual report | E6: F6 | F6: 2026-01-01 | G6: 88.9 | H6: 91.5 | I6: 94.3 | J6: 97.1 | K6: 100
A7: ebitda_h | B7: EBITDA (reported) | C7: EURm | D7: ILLUSTRATIVE - replace with SABI/Orbis or the annual report | E7: F6 | F7: 2026-01-01 | G7: 10.2 | H7: 10.8 | I7: 11.5 | J7: 12.1 | K7: 13
A8: cust_h | B8: Customers (reported) | C8: m | D8: ILLUSTRATIVE - replace (annual report KPIs / case pack) | E8: F6 | F8: 2026-01-01 | G8: 0.48 | H8: 0.486 | I8: 0.49 | J8: 0.495 | K8: 0.5

Sheet Calculations
B1: Calculations
B2: No typed numbers on this sheet: every cell is a formula fed by Inputs, Actuals or the Sensitivity controls.
B3: Period | G3: =G4&IF(G4<=Inputs!$F$46,"A","E") | H3: =H4&IF(H4<=Inputs!$F$46,"A","E") | I3: =I4&IF(I4<=Inputs!$F$46,"A","E") | J3: =J4&IF(J4<=Inputs!$F$46,"A","E") | K3: =K4&IF(K4<=Inputs!$F$46,"A","E") | L3: =L4&IF(L4<=Inputs!$F$46,"A","E") | M3: =M4&IF(M4<=Inputs!$F$46,"A","E") | N3: =N4&IF(N4<=Inputs!$F$46,"A","E") | ... P3: =P4&IF(P4<=Inputs!$F$46,"A","E")
B4: Year | G4: =Inputs!$F$45 | H4: =G4+1 | I4: =H4+1 | J4: =I4+1 | K4: =J4+1 | L4: =K4+1 | M4: =L4+1 | N4: =M4+1 | O4: =N4+1 | P4: =O4+1
B5: Years from base year (t) | G5: =G4-Inputs!$F$46 | H5: =H4-Inputs!$F$46 | I5: =I4-Inputs!$F$46 | J5: =J4-Inputs!$F$46 | K5: =K4-Inputs!$F$46 | L5: =L4-Inputs!$F$46 | M5: =M4-Inputs!$F$46 | N5: =N4-Inputs!$F$46 | ... P5: =P4-Inputs!$F$46
B7: 0. Reported history: growth, CAGR, quartiles and margins (feeds history-linked inputs)
A8: rev | B8: Revenue (reported): YoY growth | C8: % | H8: =Actuals!H6/Actuals!G6-1 | I8: =Actuals!I6/Actuals!H6-1 | J8: =Actuals!J6/Actuals!I6-1 | K8: =Actuals!K6/Actuals!J6-1
B9: Revenue (reported): CAGR 2020-2024 | C9: % | E9: =(Actuals!K6/Actuals!G6)^(1/(K$4-G$4))-1
B10: Revenue (reported): median YoY growth | C10: % | E10: =MEDIAN(H8:K8)
B11: Revenue (reported): YoY growth, lower percentile | C11: % | E11: =PERCENTILE(H8:K8,Inputs!$F$51)
B12: Revenue (reported): YoY growth, upper percentile | C12: % | E12: =PERCENTILE(H8:K8,Inputs!$F$52)
A14: ebitda_h | B14: EBITDA (reported): YoY growth | C14: % | H14: =Actuals!H7/Actuals!G7-1 | I14: =Actuals!I7/Actuals!H7-1 | J14: =Actuals!J7/Actuals!I7-1 | K14: =Actuals!K7/Actuals!J7-1
B15: EBITDA (reported): CAGR 2020-2024 | C15: % | E15: =(Actuals!K7/Actuals!G7)^(1/(K$4-G$4))-1
B16: EBITDA (reported): median YoY growth | C16: % | E16: =MEDIAN(H14:K14)
B17: EBITDA (reported): YoY growth, lower percentile | C17: % | E17: =PERCENTILE(H14:K14,Inputs!$F$51)
B18: EBITDA (reported): YoY growth, upper percentile | C18: % | E18: =PERCENTILE(H14:K14,Inputs!$F$52)
A19: ebitda_h | B19: EBITDA (reported): % of revenue | C19: % | G19: =Actuals!G7/Actuals!G6 | H19: =Actuals!H7/Actuals!H6 | I19: =Actuals!I7/Actuals!I6 | J19: =Actuals!J7/Actuals!J6 | K19: =Actuals!K7/Actuals!K6
B20: EBITDA (reported): median % of revenue | C20: % | E20: =MEDIAN(G19:K19)
B21: EBITDA (reported): % of revenue, lower percentile | C21: % | E21: =PERCENTILE(G19:K19,Inputs!$F$51)
B22: EBITDA (reported): % of revenue, upper percentile | C22: % | E22: =PERCENTILE(G19:K19,Inputs!$F$52)
A24: cust_h | B24: Customers (reported): YoY growth | C24: % | H24: =Actuals!H8/Actuals!G8-1 | I24: =Actuals!I8/Actuals!H8-1 | J24: =Actuals!J8/Actuals!I8-1 | K24: =Actuals!K8/Actuals!J8-1
B25: Customers (reported): CAGR 2020-2024 | C25: % | E25: =(Actuals!K8/Actuals!G8)^(1/(K$4-G$4))-1
B26: Customers (reported): median YoY growth | C26: % | E26: =MEDIAN(H24:K24)
B27: Customers (reported): YoY growth, lower percentile | C27: % | E27: =PERCENTILE(H24:K24,Inputs!$F$51)
B28: Customers (reported): YoY growth, upper percentile | C28: % | E28: =PERCENTILE(H24:K24,Inputs!$F$52)
B30: 1. Live inputs (Base case unless a scenario, tornado or sensitivity switch is set)
A31: cust0 | B31: Customers, base year | C31: m | D31: Inputs row 7 | E31: =Inputs!$F$7
A32: cust_g | B32: Baseline growth in customers | C32: % | D32: Inputs row 8 | E32: =IF(Sensitivity!$E$6=Inputs!$A$8,Inputs!$G$8,IF(Sensitivity!$E$6=-Inputs!$A$8,Inputs!$E$8,CHOOSE(Sensitivity!$E$5,IF(Inputs!$H$8>0,Inputs!$E$8,Inputs!$G$8),Inputs!$F$8,IF(Inputs!$H$8>0,Inputs!$G$8,Inputs!$E$8))))
A33: market | B33: Ceiling: addressable customers | C33: m | D33: Inputs row 13 | E33: =Inputs!$F$13
A34: market_g | B34: Growth in addressable customers | C34: % | D34: Inputs row 14 | E34: =IF(Sensitivity!$E$6=Inputs!$A$14,Inputs!$G$14,IF(Sensitivity!$E$6=-Inputs!$A$14,Inputs!$E$14,CHOOSE(Sensitivity!$E$5,IF(Inputs!$H$14>0,Inputs!$E$14,Inputs!$G$14),Inputs!$F$14,IF(Inputs!$H$14>0,Inputs!$G$14,Inputs!$E$14))))
A35: freq0 | B35: Purchases per customer per year | C35: x | D35: Inputs row 9 | E35: =Inputs!$F$9
A36: ticket0 | B36: Average ticket, base year | C36: EUR | D36: Inputs row 10 | E36: =Inputs!$F$10
A37: infl | B37: Price inflation | C37: % | D37: Inputs row 11 | E37: =IF(Sensitivity!$E$6=Inputs!$A$11,Inputs!$G$11,IF(Sensitivity!$E$6=-Inputs!$A$11,Inputs!$E$11,CHOOSE(Sensitivity!$E$5,IF(Inputs!$H$11>0,Inputs!$E$11,Inputs!$G$11),Inputs!$F$11,IF(Inputs!$H$11>0,Inputs!$G$11,Inputs!$E$11))))
A38: to_m | B38: Unit conversion: EUR to EURm with customers in millions | C38: x | D38: Inputs row 16 | E38: =Inputs!$F$16
A39: a_up | B39: Pillar A: peak uplift in customers | C39: % | D39: Inputs row 18 | E39: =IF(Sensitivity!$E$6=Inputs!$A$18,Inputs!$G$18,IF(Sensitivity!$E$6=-Inputs!$A$18,Inputs!$E$18,CHOOSE(Sensitivity!$E$5,IF(Inputs!$H$18>0,Inputs!$E$18,Inputs!$G$18),Inputs!$F$18,IF(Inputs!$H$18>0,Inputs!$G$18,Inputs!$E$18))))
A40: b_up | B40: Pillar B: peak uplift in purchase frequency | C40: % | D40: Inputs row 24 | E40: =IF(Sensitivity!$E$6=Inputs!$A$24,Inputs!$G$24,IF(Sensitivity!$E$6=-Inputs!$A$24,Inputs!$E$24,CHOOSE(Sensitivity!$E$5,IF(Inputs!$H$24>0,Inputs!$E$24,Inputs!$G$24),Inputs!$F$24,IF(Inputs!$H$24>0,Inputs!$G$24,Inputs!$E$24))))
A41: c_up | B41: Pillar C: peak uplift in average ticket | C41: % | D41: Inputs row 27 | E41: =IF(ISNUMBER(Sensitivity!$E$7),Sensitivity!$E$7,IF(Sensitivity!$E$6=Inputs!$A$27,Inputs!$G$27,IF(Sensitivity!$E$6=-Inputs!$A$27,Inputs!$E$27,CHOOSE(Sensitivity!$E$5,IF(Inputs!$H$27>0,Inputs!$E$27,Inputs!$G$27),Inputs!$F$27,IF(Inputs!$H$27>0,Inputs!$G$27,Inputs!$E$27)))))
A42: decay | B42: Annual erosion of initiative effects | C42: % | D42: Inputs row 19 | E42: =IF(Sensitivity!$E$6=Inputs!$A$19,Inputs!$G$19,IF(Sensitivity!$E$6=-Inputs!$A$19,Inputs!$E$19,CHOOSE(Sensitivity!$E$5,IF(Inputs!$H$19>0,Inputs!$E$19,Inputs!$G$19),Inputs!$F$19,IF(Inputs!$H$19>0,Inputs!$G$19,Inputs!$E$19))))
A43: bass_p | B43: Bass p | C43: x | D43: Inputs row 20 | E43: =IF(ISNUMBER(Sensitivity!$E$10),Sensitivity!$E$10,IF(Sensitivity!$E$6=Inputs!$A$20,Inputs!$G$20,IF(Sensitivity!$E$6=-Inputs!$A$20,Inputs!$E$20,CHOOSE(Sensitivity!$E$5,IF(Inputs!$H$20>0,Inputs!$E$20,Inputs!$G$20),Inputs!$F$20,IF(Inputs!$H$20>0,Inputs!$G$20,Inputs!$E$20)))))
A44: bass_q | B44: Bass q | C44: x | D44: Inputs row 21 | E44: =IF(Sensitivity!$E$6=Inputs!$A$21,Inputs!$G$21,IF(Sensitivity!$E$6=-Inputs!$A$21,Inputs!$E$21,CHOOSE(Sensitivity!$E$5,IF(Inputs!$H$21>0,Inputs!$E$21,Inputs!$G$21),Inputs!$F$21,IF(Inputs!$H$21>0,Inputs!$G$21,Inputs!$E$21))))
A45: c_ytp | B45: Pillar C: years to full effect (linear ramp) | C45: years | D45: Inputs row 28 | E45: =IF(Sensitivity!$E$6=Inputs!$A$28,Inputs!$G$28,IF(Sensitivity!$E$6=-Inputs!$A$28,Inputs!$E$28,CHOOSE(Sensitivity!$E$5,IF(Inputs!$H$28>0,Inputs!$E$28,Inputs!$G$28),Inputs!$F$28,IF(Inputs!$H$28>0,Inputs!$G$28,Inputs!$E$28))))
A46: a_opex | B46: Pillar A: annual cost | C46: EURm | D46: Inputs row 31 | E46: =IF(Sensitivity!$E$6=Inputs!$A$31,Inputs!$G$31,IF(Sensitivity!$E$6=-Inputs!$A$31,Inputs!$E$31,CHOOSE(Sensitivity!$E$5,IF(Inputs!$H$31>0,Inputs!$E$31,Inputs!$G$31),Inputs!$F$31,IF(Inputs!$H$31>0,Inputs!$G$31,Inputs!$E$31))))
A47: b_capex | B47: Pillar B: launch investment | C47: EURm | D47: Inputs row 32 | E47: =IF(Sensitivity!$E$6=Inputs!$A$32,Inputs!$G$32,IF(Sensitivity!$E$6=-Inputs!$A$32,Inputs!$E$32,CHOOSE(Sensitivity!$E$5,IF(Inputs!$H$32>0,Inputs!$E$32,Inputs!$G$32),Inputs!$F$32,IF(Inputs!$H$32>0,Inputs!$G$32,Inputs!$E$32))))
A48: c_opex | B48: Pillar C: annual cost | C48: EURm | D48: Inputs row 33 | E48: =IF(Sensitivity!$E$6=Inputs!$A$33,Inputs!$G$33,IF(Sensitivity!$E$6=-Inputs!$A$33,Inputs!$E$33,CHOOSE(Sensitivity!$E$5,IF(Inputs!$H$33>0,Inputs!$E$33,Inputs!$G$33),Inputs!$F$33,IF(Inputs!$H$33>0,Inputs!$G$33,Inputs!$E$33))))
A49: margin | B49: Contribution margin on incremental revenue | C49: % | D49: Inputs row 35 | E49: =IF(ISNUMBER(Sensitivity!$E$8),Sensitivity!$E$8,IF(Sensitivity!$E$6=Inputs!$A$35,Inputs!$G$35,IF(Sensitivity!$E$6=-Inputs!$A$35,Inputs!$E$35,CHOOSE(Sensitivity!$E$5,IF(Inputs!$H$35>0,Inputs!$E$35,Inputs!$G$35),Inputs!$F$35,IF(Inputs!$H$35>0,Inputs!$G$35,Inputs!$E$35)))))
A50: tax | B50: Corporate tax rate | C50: % | D50: Inputs row 36 | E50: =IF(Sensitivity!$E$6=Inputs!$A$36,Inputs!$G$36,IF(Sensitivity!$E$6=-Inputs!$A$36,Inputs!$E$36,CHOOSE(Sensitivity!$E$5,IF(Inputs!$H$36>0,Inputs!$E$36,Inputs!$G$36),Inputs!$F$36,IF(Inputs!$H$36>0,Inputs!$G$36,Inputs!$E$36))))
A51: rf | B51: Risk-free rate | C51: % | D51: Inputs row 37 | E51: =IF(Sensitivity!$E$6=Inputs!$A$37,Inputs!$G$37,IF(Sensitivity!$E$6=-Inputs!$A$37,Inputs!$E$37,CHOOSE(Sensitivity!$E$5,IF(Inputs!$H$37>0,Inputs!$E$37,Inputs!$G$37),Inputs!$F$37,IF(Inputs!$H$37>0,Inputs!$G$37,Inputs!$E$37))))
A52: beta | B52: Levered beta | C52: x | D52: Inputs row 38 | E52: =IF(Sensitivity!$E$6=Inputs!$A$38,Inputs!$G$38,IF(Sensitivity!$E$6=-Inputs!$A$38,Inputs!$E$38,CHOOSE(Sensitivity!$E$5,IF(Inputs!$H$38>0,Inputs!$E$38,Inputs!$G$38),Inputs!$F$38,IF(Inputs!$H$38>0,Inputs!$G$38,Inputs!$E$38))))
A53: erp | B53: Equity risk premium | C53: % | D53: Inputs row 39 | E53: =IF(Sensitivity!$E$6=Inputs!$A$39,Inputs!$G$39,IF(Sensitivity!$E$6=-Inputs!$A$39,Inputs!$E$39,CHOOSE(Sensitivity!$E$5,IF(Inputs!$H$39>0,Inputs!$E$39,Inputs!$G$39),Inputs!$F$39,IF(Inputs!$H$39>0,Inputs!$G$39,Inputs!$E$39))))
A54: kd | B54: Pre-tax cost of debt | C54: % | D54: Inputs row 40 | E54: =IF(Sensitivity!$E$6=Inputs!$A$40,Inputs!$G$40,IF(Sensitivity!$E$6=-Inputs!$A$40,Inputs!$E$40,CHOOSE(Sensitivity!$E$5,IF(Inputs!$H$40>0,Inputs!$E$40,Inputs!$G$40),Inputs!$F$40,IF(Inputs!$H$40>0,Inputs!$G$40,Inputs!$E$40))))
A55: wd | B55: Debt weight D/(D+E) | C55: % | D55: Inputs row 41 | E55: =IF(Sensitivity!$E$6=Inputs!$A$41,Inputs!$G$41,IF(Sensitivity!$E$6=-Inputs!$A$41,Inputs!$E$41,CHOOSE(Sensitivity!$E$5,IF(Inputs!$H$41>0,Inputs!$E$41,Inputs!$G$41),Inputs!$F$41,IF(Inputs!$H$41>0,Inputs!$G$41,Inputs!$E$41))))
A56: first_hist_year | B56: First historical year shown | C56: year | D56: Inputs row 45 | E56: =Inputs!$F$45
A57: base_year | B57: Base year (last reported actuals) | C57: year | D57: Inputs row 46 | E57: =Inputs!$F$46
A58: growth_cap | B58: Growth cap: max YoY growth of target revenue | C58: % | D58: Inputs row 47 | E58: =Inputs!$F$47
A59: calib_tol | B59: Tolerance: baseline vs reported revenue | C59: % | D59: Inputs row 48 | E59: =Inputs!$F$48
A60: sum_tol | B60: Tolerance: totals vs sum of parts | C60: abs | D60: Inputs row 49 | E60: =Inputs!$F$49
A61: tie_step | B61: Tornado tie-break step (keeps ranks unique when two swings are equal) | C61: abs | D61: Inputs row 50 | E61: =Inputs!$F$50
A62: a1_launch | B62: Launch year: Initiative A1 | C62: year | D62: Inputs row 22 | E62: =Inputs!$F$22
A63: b1_launch | B63: Launch year: Initiative B1 | C63: year | D63: Inputs row 25 | E63: =Inputs!$F$25
A64: c1_launch | B64: Launch year: Initiative C1 | C64: year | D64: Inputs row 29 | E64: =Inputs!$F$29
A65: tv_g | B65: Terminal growth of incremental FCF after the horizon | C65: % | D65: Inputs row 42 | E65: =IF(ISNUMBER(Sensitivity!$E$9),Sensitivity!$E$9,IF(Sensitivity!$E$6=Inputs!$A$42,Inputs!$G$42,IF(Sensitivity!$E$6=-Inputs!$A$42,Inputs!$E$42,CHOOSE(Sensitivity!$E$5,IF(Inputs!$H$42>0,Inputs!$E$42,Inputs!$G$42),Inputs!$F$42,IF(Inputs!$H$42>0,Inputs!$G$42,Inputs!$E$42)))))
A66: tv_on | B66: Include terminal value (1 = yes, 0 = horizon only) | C66: switch | D66: Inputs row 43 | E66: =Inputs!$F$43
A67: hist_p_low | B67: History band: lower percentile of YoY growth | C67: % | D67: Inputs row 51 | E67: =Inputs!$F$51
A68: hist_p_high | B68: History band: upper percentile of YoY growth | C68: % | D68: Inputs row 52 | E68: =Inputs!$F$52
A69: hist_tol | B69: History band: tolerance around the band (baseline growth vs history) | C69: % | D69: Inputs row 53 | E69: =Inputs!$F$53
B71: 2. Discount rate (WACC from sourced inputs)
B72: Cost of equity (CAPM) | C72: % | E72: =$E$51+$E$52*$E$53
B73: After-tax cost of debt | C73: % | E73: =$E$54*(1-$E$50)
B74: WACC | C74: % | E74: =(1-$E$55)*$E$72+$E$55*$E$73
B76: 3. Driver tree leaves: baseline, ceiling, initiative uplift (S-curve x decay), with strategy
A77: customers | B77: Baseline: Customers | C77: m | K77: =$E$31 | L77: =K77*(1+$E$32) | M77: =L77*(1+$E$32) | N77: =M77*(1+$E$32) | O77: =N77*(1+$E$32) | P77: =O77*(1+$E$32)
B78: Ceiling: addressable Customers (market / capacity) | C78: m | K78: =$E$33 | L78: =K78*(1+$E$34) | M78: =L78*(1+$E$34) | N78: =M78*(1+$E$34) | O78: =N78*(1+$E$34) | P78: =O78*(1+$E$34)
A79: a1 | B79: Adoption (bass curve): Initiative A1 | C79: % | L79: =IF(L$4>=$E$62,(1-EXP(-($E$43+$E$44)*(L$4-$E$62+1)))/(1+($E$44/$E$43)*EXP(-($E$43+$E$44)*(L$4-$E$62+1))),0) | M79: =IF(M$4>=$E$62,(1-EXP(-($E$43+$E$44)*(M$4-$E$62+1)))/(1+($E$44/$E$43)*EXP(-($E$43+$E$44)*(M$4-$E$62+1))),0) | N79: =IF(N$4>=$E$62,(1-EXP(-($E$43+$E$44)*(N$4-$E$62+1)))/(1+($E$44/$E$43)*EXP(-($E$43+$E$44)*(N$4-$E$62+1))),0) | O79: =IF(O$4>=$E$62,(1-EXP(-($E$43+$E$44)*(O$4-$E$62+1)))/(1+($E$44/$E$43)*EXP(-($E$43+$E$44)*(O$4-$E$62+1))),0) | P79: =IF(P$4>=$E$62,(1-EXP(-($E$43+$E$44)*(P$4-$E$62+1)))/(1+($E$44/$E$43)*EXP(-($E$43+$E$44)*(P$4-$E$62+1))),0)
A80: a1 | B80: Effect retention after decay: Initiative A1 | C80: % | L80: =IF(L$4>=$E$62,(1-$E$42)^(L$4-$E$62),0) | M80: =IF(M$4>=$E$62,(1-$E$42)^(M$4-$E$62),0) | N80: =IF(N$4>=$E$62,(1-$E$42)^(N$4-$E$62),0) | O80: =IF(O$4>=$E$62,(1-$E$42)^(O$4-$E$62),0) | P80: =IF(P$4>=$E$62,(1-$E$42)^(P$4-$E$62),0)
A81: a1 | B81: Uplift on Customers from Initiative A1 (%) | C81: % | L81: =$E$39*L79*L80 | M81: =$E$39*M79*M80 | N81: =$E$39*N79*N80 | O81: =$E$39*O79*O80 | P81: =$E$39*P79*P80
B82: Total uplift on Customers (%) | C82: % | L82: =L81 | M82: =M81 | N82: =N81 | O82: =O81 | P82: =P81
A83: customers | B83: Customers with strategy | C83: m | K83: =MIN(K77,K78) | L83: =MIN(L77*(1+L82),L78) | M83: =MIN(M77*(1+M82),M78) | N83: =MIN(N77*(1+N82),N78) | O83: =MIN(O77*(1+O82),O78) | P83: =MIN(P77*(1+P82),P78)
B84: Baseline penetration of addressable market (% of ceiling): Customers | C84: % | K84: =K77/K78 | L84: =L77/L78 | M84: =M77/M78 | N84: =N77/N78 | O84: =O77/O78 | P84: =P77/P78
B85: Penetration of addressable market (% of ceiling): Customers | C85: % | K85: =K83/K78 | L85: =L83/L78 | M85: =M83/M78 | N85: =N83/N78 | O85: =O83/O78 | P85: =P83/P78
B86: Effective uplift factor after ceiling: Customers | C86: x | L86: =L83/L77 | M86: =M83/M77 | N86: =N83/N77 | O86: =O83/O77 | P86: =P83/P77
A88: freq | B88: Baseline: Purchases per customer | C88: x | K88: =$E$35 | L88: =K88 | M88: =L88 | N88: =M88 | O88: =N88 | P88: =O88
A89: b1 | B89: Adoption (bass curve): Initiative B1 | C89: % | L89: =IF(L$4>=$E$63,(1-EXP(-($E$43+$E$44)*(L$4-$E$63+1)))/(1+($E$44/$E$43)*EXP(-($E$43+$E$44)*(L$4-$E$63+1))),0) | M89: =IF(M$4>=$E$63,(1-EXP(-($E$43+$E$44)*(M$4-$E$63+1)))/(1+($E$44/$E$43)*EXP(-($E$43+$E$44)*(M$4-$E$63+1))),0) | N89: =IF(N$4>=$E$63,(1-EXP(-($E$43+$E$44)*(N$4-$E$63+1)))/(1+($E$44/$E$43)*EXP(-($E$43+$E$44)*(N$4-$E$63+1))),0) | O89: =IF(O$4>=$E$63,(1-EXP(-($E$43+$E$44)*(O$4-$E$63+1)))/(1+($E$44/$E$43)*EXP(-($E$43+$E$44)*(O$4-$E$63+1))),0) | P89: =IF(P$4>=$E$63,(1-EXP(-($E$43+$E$44)*(P$4-$E$63+1)))/(1+($E$44/$E$43)*EXP(-($E$43+$E$44)*(P$4-$E$63+1))),0)
A90: b1 | B90: Effect retention after decay: Initiative B1 | C90: % | L90: =IF(L$4>=$E$63,(1-$E$42)^(L$4-$E$63),0) | M90: =IF(M$4>=$E$63,(1-$E$42)^(M$4-$E$63),0) | N90: =IF(N$4>=$E$63,(1-$E$42)^(N$4-$E$63),0) | O90: =IF(O$4>=$E$63,(1-$E$42)^(O$4-$E$63),0) | P90: =IF(P$4>=$E$63,(1-$E$42)^(P$4-$E$63),0)
A91: b1 | B91: Uplift on Purchases per customer from Initiative B1 (%) | C91: % | L91: =$E$40*L89*L90 | M91: =$E$40*M89*M90 | N91: =$E$40*N89*N90 | O91: =$E$40*O89*O90 | P91: =$E$40*P89*P90
B92: Total uplift on Purchases per customer (%) | C92: % | L92: =L91 | M92: =M91 | N92: =N91 | O92: =O91 | P92: =P91
A93: freq | B93: Purchases per customer with strategy | C93: x | K93: =K88 | L93: =L88*(1+L92) | M93: =M88*(1+M92) | N93: =N88*(1+N92) | O93: =O88*(1+O92) | P93: =P88*(1+P92)
B94: Effective uplift factor after ceiling: Purchases per customer | C94: x | L94: =L93/L88 | M94: =M93/M88 | N94: =N93/N88 | O94: =O93/O88 | P94: =P93/P88
A96: ticket | B96: Baseline: Average ticket | C96: EUR | K96: =$E$36 | L96: =K96*(1+$E$37) | M96: =L96*(1+$E$37) | N96: =M96*(1+$E$37) | O96: =N96*(1+$E$37) | P96: =O96*(1+$E$37)
A97: c1 | B97: Adoption (linear curve): Initiative C1 | C97: % | L97: =IF(L$4>=$E$64,MIN(1,(L$4-$E$64+1)/$E$45),0) | M97: =IF(M$4>=$E$64,MIN(1,(M$4-$E$64+1)/$E$45),0) | N97: =IF(N$4>=$E$64,MIN(1,(N$4-$E$64+1)/$E$45),0) | O97: =IF(O$4>=$E$64,MIN(1,(O$4-$E$64+1)/$E$45),0) | P97: =IF(P$4>=$E$64,MIN(1,(P$4-$E$64+1)/$E$45),0)
A98: c1 | B98: Effect retention after decay: Initiative C1 | C98: % | L98: =IF(L$4>=$E$64,(1-$E$42)^(L$4-$E$64),0) | M98: =IF(M$4>=$E$64,(1-$E$42)^(M$4-$E$64),0) | N98: =IF(N$4>=$E$64,(1-$E$42)^(N$4-$E$64),0) | O98: =IF(O$4>=$E$64,(1-$E$42)^(O$4-$E$64),0) | P98: =IF(P$4>=$E$64,(1-$E$42)^(P$4-$E$64),0)
A99: c1 | B99: Uplift on Average ticket from Initiative C1 (%) | C99: % | L99: =$E$41*L97*L98 | M99: =$E$41*M97*M98 | N99: =$E$41*N97*N98 | O99: =$E$41*O97*O98 | P99: =$E$41*P97*P98
B100: Total uplift on Average ticket (%) | C100: % | L100: =L99 | M100: =M99 | N100: =N99 | O100: =O99 | P100: =P99
A101: ticket | B101: Average ticket with strategy | C101: EUR | K101: =K96 | L101: =L96*(1+L100) | M101: =M96*(1+M100) | N101: =N96*(1+N100) | O101: =O96*(1+O100) | P101: =P96*(1+P100)
B102: Effective uplift factor after ceiling: Average ticket | C102: x | L102: =L101/L96 | M102: =M101/M96 | N102: =N101/N96 | O102: =O101/O96 | P102: =P101/P96
B104: 4. Revenue streams = product of leaves; incremental revenue split by leaf (log shares)
A105: core | B105: Baseline revenue: Core revenue | C105: EURm | K105: =K77*K88*K96*$E$38 | L105: =L77*L88*L96*$E$38 | M105: =M77*M88*M96*$E$38 | N105: =N77*N88*N96*$E$38 | O105: =O77*O88*O96*$E$38 | P105: =P77*P88*P96*$E$38
A106: core | B106: Revenue with strategy: Core revenue | C106: EURm | K106: =K83*K93*K101*$E$38 | L106: =L83*L93*L101*$E$38 | M106: =M83*M93*M101*$E$38 | N106: =N83*N93*N101*$E$38 | O106: =O83*O93*O101*$E$38 | P106: =P83*P93*P101*$E$38
A107: core | B107: Incremental revenue: Core revenue | C107: EURm | L107: =L106-L105 | M107: =M106-M105 | N107: =N106-N105 | O107: =O106-O105 | P107: =P106-P105
B108: Sum of log uplift factors: Core revenue | C108: x | L108: =LN(L86)+LN(L94)+LN(L102) | M108: =LN(M86)+LN(M94)+LN(M102) | N108: =LN(N86)+LN(N94)+LN(N102) | O108: =LN(O86)+LN(O94)+LN(O102) | P108: =LN(P86)+LN(P94)+LN(P102)
B109: Log share of uplift: Customers in Core revenue | C109: % | L109: =IF(L108=0,0,LN(L86)/L108) | M109: =IF(M108=0,0,LN(M86)/M108) | N109: =IF(N108=0,0,LN(N86)/N108) | O109: =IF(O108=0,0,LN(O86)/O108) | P109: =IF(P108=0,0,LN(P86)/P108)
...

Sheet Outputs
B1: Outputs - Example Co - three-pillar impact model (TEMPLATE: replace every input)
B2: Currency: EURm. All cells link to Calculations.
B3: Period | G3: =Calculations!G3 | H3: =Calculations!H3 | I3: =Calculations!I3 | J3: =Calculations!J3 | K3: =Calculations!K3 | L3: =Calculations!L3 | M3: =Calculations!M3 | N3: =Calculations!N3 | ... P3: =Calculations!P3
B4: Year | G4: =Calculations!G4 | H4: =Calculations!H4 | I4: =Calculations!I4 | J4: =Calculations!J4 | K4: =Calculations!K4 | L4: =Calculations!L4 | M4: =Calculations!M4 | N4: =Calculations!N4 | ... P4: =Calculations!P4
B6: Headline results (base case unless Sensitivity switches are set)
B7: NPV of strategy at WACC | C7: EURm | E7: =Calculations!$E$172
B8: of which PV of terminal value | C8: EURm | E8: =Calculations!$E$171
B9: Horizon-only NPV (no terminal value) | C9: EURm | E9: =Calculations!$E$169
B10: IRR | C10: % | E10: =Calculations!$E$173
B11: Payback (years after base year) | C11: years | E11: =Calculations!$E$174
B12: WACC | C12: % | E12: =Calculations!$E$74
B13: Incremental revenue in 2029 | C13: EURm | E13: =Calculations!$E$176
B14: Incremental EBIT in 2029 | C14: EURm | E14: =Calculations!$E$177
B15: Cumulative incremental revenue | C15: EURm | E15: =Calculations!$E$175
B16: Baseline revenue in 2029 | C16: EURm | E16: =Calculations!$E$188
B17: Target revenue in 2029 | C17: EURm | E17: =Calculations!$E$189
B19: Base case vs history
B20: Reported revenue CAGR 2020-2024 | C20: % | E20: =Calculations!$E$9
B21: Reported revenue: median YoY growth | C21: % | E21: =Calculations!$E$10
B22: Reported revenue: YoY growth, lower percentile | C22: % | E22: =Calculations!$E$11
B23: Reported revenue: YoY growth, upper percentile | C23: % | E23: =Calculations!$E$12
B24: Baseline revenue CAGR 2024-2029 (do nothing) | C24: % | E24: =Calculations!$E$194
B25: EBITDA (reported): median % of revenue | C25: % | E25: =Calculations!$E$20
B27: Revenue path
B28: Reported revenue (actuals) | C28: EURm | G28: =Calculations!G120 | H28: =Calculations!H120 | I28: =Calculations!I120 | J28: =Calculations!J120 | K28: =Calculations!K120
B29: Baseline revenue (do nothing) | C29: EURm | K29: =Calculations!K117 | L29: =Calculations!L117 | M29: =Calculations!M117 | N29: =Calculations!N117 | O29: =Calculations!O117 | P29: =Calculations!P117
B30: Target revenue (with strategy) | C30: EURm | K30: =Calculations!K118 | L30: =Calculations!L118 | M30: =Calculations!M118 | N30: =Calculations!N118 | O30: =Calculations!O118 | P30: =Calculations!P118
B32: Incremental revenue by pillar
B33: Incremental revenue: Pillar A | C33: EURm | L33: =Calculations!L131 | M33: =Calculations!M131 | N33: =Calculations!N131 | O33: =Calculations!O131 | P33: =Calculations!P131
B34: Incremental revenue: Pillar B | C34: EURm | L34: =Calculations!L132 | M34: =Calculations!M132 | N34: =Calculations!N132 | O34: =Calculations!O132 | P34: =Calculations!P132
B35: Incremental revenue: Pillar C | C35: EURm | L35: =Calculations!L133 | M35: =Calculations!M133 | N35: =Calculations!N133 | O35: =Calculations!O133 | P35: =Calculations!P133
B36: Total incremental revenue | C36: EURm | L36: =SUM(L33:L35) | M36: =SUM(M33:M35) | N36: =SUM(N33:N35) | O36: =SUM(O33:O35) | P36: =SUM(P33:P35)
B38: Incremental revenue by initiative
B39: Incremental revenue: Initiative A1 | C39: EURm | L39: =Calculations!L125 | M39: =Calculations!M125 | N39: =Calculations!N125 | O39: =Calculations!O125 | P39: =Calculations!P125
B40: Incremental revenue: Initiative B1 | C40: EURm | L40: =Calculations!L126 | M40: =Calculations!M126 | N40: =Calculations!N126 | O40: =Calculations!O126 | P40: =Calculations!P126
B41: Incremental revenue: Initiative C1 | C41: EURm | L41: =Calculations!L127 | M41: =Calculations!M127 | N41: =Calculations!N127 | O41: =Calculations!O127 | P41: =Calculations!P127
B42: Total incremental revenue | C42: EURm | L42: =SUM(L39:L41) | M42: =SUM(M39:M41) | N42: =SUM(N39:N41) | O42: =SUM(O39:O41) | P42: =SUM(P39:P41)
B44: Incremental EBIT by pillar (revenue x margin + cost savings - opex)
B45: Incremental EBIT: Pillar A | C45: EURm | L45: =Calculations!L153 | M45: =Calculations!M153 | N45: =Calculations!N153 | O45: =Calculations!O153 | P45: =Calculations!P153
B46: Incremental EBIT: Pillar B | C46: EURm | L46: =Calculations!L154 | M46: =Calculations!M154 | N46: =Calculations!N154 | O46: =Calculations!O154 | P46: =Calculations!P154
B47: Incremental EBIT: Pillar C | C47: EURm | L47: =Calculations!L155 | M47: =Calculations!M155 | N47: =Calculations!N155 | O47: =Calculations!O155 | P47: =Calculations!P155
B48: Total incremental EBIT | C48: EURm | L48: =SUM(L45:L47) | M48: =SUM(M45:M47) | N48: =SUM(N45:N47) | O48: =SUM(O45:O47) | P48: =SUM(P45:P47)
B50: NPV by initiative (standalone; adds up to the strategy NPV)
B51: NPV: Initiative A1 | C51: EURm | E51: =Calculations!$E$181
B52: NPV: Initiative B1 | C52: EURm | E52: =Calculations!$E$183
B53: NPV: Initiative C1 | C53: EURm | E53: =Calculations!$E$185
B55: Incremental EBIT by initiative
B56: Incremental EBIT: Initiative A1 | C56: EURm | L56: =Calculations!L149 | M56: =Calculations!M149 | N56: =Calculations!N149 | O56: =Calculations!O149 | P56: =Calculations!P149
B57: Incremental EBIT: Initiative B1 | C57: EURm | L57: =Calculations!L150 | M57: =Calculations!M150 | N57: =Calculations!N150 | O57: =Calculations!O150 | P57: =Calculations!P150
B58: Incremental EBIT: Initiative C1 | C58: EURm | L58: =Calculations!L151 | M58: =Calculations!M151 | N58: =Calculations!N151 | O58: =Calculations!O151 | P58: =Calculations!P151
B59: Total incremental EBIT | C59: EURm | L59: =SUM(L56:L58) | M59: =SUM(M56:M58) | N59: =SUM(N56:N58) | O59: =SUM(O56:O58) | P59: =SUM(P56:P58)
B61: Incremental profit and cash
B62: Incremental EBIT | C62: EURm | L62: =Calculations!L160 | M62: =Calculations!M160 | N62: =Calculations!N160 | O62: =Calculations!O160 | P62: =Calculations!P160
B63: Incremental free cash flow | C63: EURm | L63: =Calculations!L163 | M63: =Calculations!M163 | N63: =Calculations!N163 | O63: =Calculations!O163 | P63: =Calculations!P163
B64: Cumulative incremental free cash flow | C64: EURm | L64: =Calculations!L166 | M64: =Calculations!M166 | N64: =Calculations!N166 | O64: =Calculations!O166 | P64: =Calculations!P166

Sheet Bridge
B1: Revenue bridge 2029: baseline to target (EURm)
B2: One-slide impact bridge. Columns D-G drive the waterfall chart.
B4: Step | C4: Value | D4: Invisible base | E4: Increase | F4: Decrease | G4: Level | H4: Running total
B5: Baseline revenue 2029 (do nothing) | C5: =Calculations!P117 | G5: =C5 | H5: =C5
B6: Pillar A: Initiative A1 | C6: =Calculations!P125 | D6: =IF(C6>=0,H5,H5+C6) | E6: =MAX(C6,0) | F6: =MAX(-C6,0) | H6: =H5+C6
B7: Pillar B: Initiative B1 | C7: =Calculations!P126 | D7: =IF(C7>=0,H6,H6+C7) | E7: =MAX(C7,0) | F7: =MAX(-C7,0) | H7: =H6+C7
B8: Pillar C: Initiative C1 | C8: =Calculations!P127 | D8: =IF(C8>=0,H7,H7+C8) | E8: =MAX(C8,0) | F8: =MAX(-C8,0) | H8: =H7+C8
B9: Target revenue 2029 (with strategy) | C9: =Calculations!P118 | G9: =C9 | H9: =C9
B11: Incremental EBIT bridge 2029 by initiative (EURm)
B12: Do nothing (no incremental EBIT) | C12: =0 | G12: =C12 | H12: =C12
B13: Pillar A: Initiative A1 | C13: =Calculations!P149 | D13: =IF(C13>=0,H12,H12+C13) | E13: =MAX(C13,0) | F13: =MAX(-C13,0) | H13: =H12+C13
B14: Pillar B: Initiative B1 | C14: =Calculations!P150 | D14: =IF(C14>=0,H13,H13+C14) | E14: =MAX(C14,0) | F14: =MAX(-C14,0) | H14: =H13+C14
B15: Pillar C: Initiative C1 | C15: =Calculations!P151 | D15: =IF(C15>=0,H14,H14+C15) | E15: =MAX(C15,0) | F15: =MAX(-C15,0) | H15: =H14+C15
B16: Incremental EBIT 2029 (with strategy) | C16: =Calculations!P160 | G16: =C16 | H16: =C16

Sheet Sensitivity
B1: Sensitivity - scenarios, tornado, two-way tables
B2: Live Excel Data Tables (Data > What-If). Leave the orange controls at Base / 0 / blank.
B4: Controls
B5: Scenario switch (1 = Low, 2 = Base, 3 = High) | E5: 2
B6: Tornado selector (0 = off; set by the tornado Data Tables) | E6: 0
B7: Override for two-way table: Pillar C: peak uplift in average ticket (leave blank)
B8: Override for two-way table: Contribution margin on incremental revenue (leave blank)
B9: Override for two-way table: Terminal growth of incremental FCF after the horizon (leave blank)
B10: Override for two-way table: Bass p (leave blank)
B13: Scenarios: Low / Base / High (every ranged input moves to its pessimistic / optimistic end)
B14: Scenario | C14: Switch | D14: NPV | E14: Incr. revenue 2029 | F14: Incr. EBIT 2029 | G14: Cumulative incr. revenue
B15: Live (current switches) | D15: =Calculations!$E$172 | E15: =Calculations!$E$176 | F15: =Calculations!$E$177 | G15: =Calculations!$E$175
B16: Low | C16: 1
B17: Base | C17: 2
B18: High | C18: 3
B21: Tornado: NPV with each input at its low and high value, others at base
B22: Input | C22: Selector (low) | D22: NPV at low | E22: Selector (high) | F22: NPV at high | G22: Base NPV | H22: Delta at low | I22: Delta at high | J22: Swing | K22: Rank | L22: Sort key
B23: Live NPV | D23: =Calculations!$E$172 | F23: =Calculations!$E$172
B24: =Inputs!$B$8 | C24: =-Inputs!$A$8 | E24: =Inputs!$A$8 | G24: =Calculations!$E$172 | H24: =D24-G24 | I24: =F24-G24 | J24: =ABS(F24-D24) | K24: =RANK(L24,$L$24:$L$43) | L24: =J24+ROWS($J$24:J24)*Inputs!$F$50
B25: =Inputs!$B$11 | C25: =-Inputs!$A$11 | E25: =Inputs!$A$11 | G25: =Calculations!$E$172 | H25: =D25-G25 | I25: =F25-G25 | J25: =ABS(F25-D25) | K25: =RANK(L25,$L$24:$L$43) | L25: =J25+ROWS($J$24:J25)*Inputs!$F$50
B26: =Inputs!$B$18 | C26: =-Inputs!$A$18 | E26: =Inputs!$A$18 | G26: =Calculations!$E$172 | H26: =D26-G26 | I26: =F26-G26 | J26: =ABS(F26-D26) | K26: =RANK(L26,$L$24:$L$43) | L26: =J26+ROWS($J$24:J26)*Inputs!$F$50
B27: =Inputs!$B$19 | C27: =-Inputs!$A$19 | E27: =Inputs!$A$19 | G27: =Calculations!$E$172 | H27: =D27-G27 | I27: =F27-G27 | J27: =ABS(F27-D27) | K27: =RANK(L27,$L$24:$L$43) | L27: =J27+ROWS($J$24:J27)*Inputs!$F$50
B28: =Inputs!$B$20 | C28: =-Inputs!$A$20 | E28: =Inputs!$A$20 | G28: =Calculations!$E$172 | H28: =D28-G28 | I28: =F28-G28 | J28: =ABS(F28-D28) | K28: =RANK(L28,$L$24:$L$43) | L28: =J28+ROWS($J$24:J28)*Inputs!$F$50
B29: =Inputs!$B$21 | C29: =-Inputs!$A$21 | E29: =Inputs!$A$21 | G29: =Calculations!$E$172 | H29: =D29-G29 | I29: =F29-G29 | J29: =ABS(F29-D29) | K29: =RANK(L29,$L$24:$L$43) | L29: =J29+ROWS($J$24:J29)*Inputs!$F$50
B30: =Inputs!$B$24 | C30: =-Inputs!$A$24 | E30: =Inputs!$A$24 | G30: =Calculations!$E$172 | H30: =D30-G30 | I30: =F30-G30 | J30: =ABS(F30-D30) | K30: =RANK(L30,$L$24:$L$43) | L30: =J30+ROWS($J$24:J30)*Inputs!$F$50
B31: =Inputs!$B$27 | C31: =-Inputs!$A$27 | E31: =Inputs!$A$27 | G31: =Calculations!$E$172 | H31: =D31-G31 | I31: =F31-G31 | J31: =ABS(F31-D31) | K31: =RANK(L31,$L$24:$L$43) | L31: =J31+ROWS($J$24:J31)*Inputs!$F$50
B32: =Inputs!$B$28 | C32: =-Inputs!$A$28 | E32: =Inputs!$A$28 | G32: =Calculations!$E$172 | H32: =D32-G32 | I32: =F32-G32 | J32: =ABS(F32-D32) | K32: =RANK(L32,$L$24:$L$43) | L32: =J32+ROWS($J$24:J32)*Inputs!$F$50
B33: =Inputs!$B$31 | C33: =-Inputs!$A$31 | E33: =Inputs!$A$31 | G33: =Calculations!$E$172 | H33: =D33-G33 | I33: =F33-G33 | J33: =ABS(F33-D33) | K33: =RANK(L33,$L$24:$L$43) | L33: =J33+ROWS($J$24:J33)*Inputs!$F$50
B34: =Inputs!$B$32 | C34: =-Inputs!$A$32 | E34: =Inputs!$A$32 | G34: =Calculations!$E$172 | H34: =D34-G34 | I34: =F34-G34 | J34: =ABS(F34-D34) | K34: =RANK(L34,$L$24:$L$43) | L34: =J34+ROWS($J$24:J34)*Inputs!$F$50
B35: =Inputs!$B$33 | C35: =-Inputs!$A$33 | E35: =Inputs!$A$33 | G35: =Calculations!$E$172 | H35: =D35-G35 | I35: =F35-G35 | J35: =ABS(F35-D35) | K35: =RANK(L35,$L$24:$L$43) | L35: =J35+ROWS($J$24:J35)*Inputs!$F$50
B36: =Inputs!$B$35 | C36: =-Inputs!$A$35 | E36: =Inputs!$A$35 | G36: =Calculations!$E$172 | H36: =D36-G36 | I36: =F36-G36 | J36: =ABS(F36-D36) | K36: =RANK(L36,$L$24:$L$43) | L36: =J36+ROWS($J$24:J36)*Inputs!$F$50
B37: =Inputs!$B$36 | C37: =-Inputs!$A$36 | E37: =Inputs!$A$36 | G37: =Calculations!$E$172 | H37: =D37-G37 | I37: =F37-G37 | J37: =ABS(F37-D37) | K37: =RANK(L37,$L$24:$L$43) | L37: =J37+ROWS($J$24:J37)*Inputs!$F$50
B38: =Inputs!$B$37 | C38: =-Inputs!$A$37 | E38: =Inputs!$A$37 | G38: =Calculations!$E$172 | H38: =D38-G38 | I38: =F38-G38 | J38: =ABS(F38-D38) | K38: =RANK(L38,$L$24:$L$43) | L38: =J38+ROWS($J$24:J38)*Inputs!$F$50
B39: =Inputs!$B$38 | C39: =-Inputs!$A$38 | E39: =Inputs!$A$38 | G39: =Calculations!$E$172 | H39: =D39-G39 | I39: =F39-G39 | J39: =ABS(F39-D39) | K39: =RANK(L39,$L$24:$L$43) | L39: =J39+ROWS($J$24:J39)*Inputs!$F$50
B40: =Inputs!$B$39 | C40: =-Inputs!$A$39 | E40: =Inputs!$A$39 | G40: =Calculations!$E$172 | H40: =D40-G40 | I40: =F40-G40 | J40: =ABS(F40-D40) | K40: =RANK(L40,$L$24:$L$43) | L40: =J40+ROWS($J$24:J40)*Inputs!$F$50
B41: =Inputs!$B$40 | C41: =-Inputs!$A$40 | E41: =Inputs!$A$40 | G41: =Calculations!$E$172 | H41: =D41-G41 | I41: =F41-G41 | J41: =ABS(F41-D41) | K41: =RANK(L41,$L$24:$L$43) | L41: =J41+ROWS($J$24:J41)*Inputs!$F$50
B42: =Inputs!$B$41 | C42: =-Inputs!$A$41 | E42: =Inputs!$A$41 | G42: =Calculations!$E$172 | H42: =D42-G42 | I42: =F42-G42 | J42: =ABS(F42-D42) | K42: =RANK(L42,$L$24:$L$43) | L42: =J42+ROWS($J$24:J42)*Inputs!$F$50
B43: =Inputs!$B$42 | C43: =-Inputs!$A$42 | E43: =Inputs!$A$42 | G43: =Calculations!$E$172 | H43: =D43-G43 | I43: =F43-G43 | J43: =ABS(F43-D43) | K43: =RANK(L43,$L$24:$L$43) | L43: =J43+ROWS($J$24:J43)*Inputs!$F$50
B46: Tornado chart data: top 10 inputs by swing
B47: Rank | C47: Input | D47: Delta at low | E47: Delta at high
B48: =ROWS($B$48:B48) | C48: =INDEX($B$24:$B$43,MATCH(B48,$K$24:$K$43,0)) | D48: =INDEX($H$24:$H$43,MATCH(B48,$K$24:$K$43,0)) | E48: =INDEX($I$24:$I$43,MATCH(B48,$K$24:$K$43,0))
B49: =ROWS($B$48:B49) | C49: =INDEX($B$24:$B$43,MATCH(B49,$K$24:$K$43,0)) | D49: =INDEX($H$24:$H$43,MATCH(B49,$K$24:$K$43,0)) | E49: =INDEX($I$24:$I$43,MATCH(B49,$K$24:$K$43,0))
B50: =ROWS($B$48:B50) | C50: =INDEX($B$24:$B$43,MATCH(B50,$K$24:$K$43,0)) | D50: =INDEX($H$24:$H$43,MATCH(B50,$K$24:$K$43,0)) | E50: =INDEX($I$24:$I$43,MATCH(B50,$K$24:$K$43,0))
B51: =ROWS($B$48:B51) | C51: =INDEX($B$24:$B$43,MATCH(B51,$K$24:$K$43,0)) | D51: =INDEX($H$24:$H$43,MATCH(B51,$K$24:$K$43,0)) | E51: =INDEX($I$24:$I$43,MATCH(B51,$K$24:$K$43,0))
B52: =ROWS($B$48:B52) | C52: =INDEX($B$24:$B$43,MATCH(B52,$K$24:$K$43,0)) | D52: =INDEX($H$24:$H$43,MATCH(B52,$K$24:$K$43,0)) | E52: =INDEX($I$24:$I$43,MATCH(B52,$K$24:$K$43,0))
B53: =ROWS($B$48:B53) | C53: =INDEX($B$24:$B$43,MATCH(B53,$K$24:$K$43,0)) | D53: =INDEX($H$24:$H$43,MATCH(B53,$K$24:$K$43,0)) | E53: =INDEX($I$24:$I$43,MATCH(B53,$K$24:$K$43,0))
B54: =ROWS($B$48:B54) | C54: =INDEX($B$24:$B$43,MATCH(B54,$K$24:$K$43,0)) | D54: =INDEX($H$24:$H$43,MATCH(B54,$K$24:$K$43,0)) | E54: =INDEX($I$24:$I$43,MATCH(B54,$K$24:$K$43,0))
B55: =ROWS($B$48:B55) | C55: =INDEX($B$24:$B$43,MATCH(B55,$K$24:$K$43,0)) | D55: =INDEX($H$24:$H$43,MATCH(B55,$K$24:$K$43,0)) | E55: =INDEX($I$24:$I$43,MATCH(B55,$K$24:$K$43,0))
B56: =ROWS($B$48:B56) | C56: =INDEX($B$24:$B$43,MATCH(B56,$K$24:$K$43,0)) | D56: =INDEX($H$24:$H$43,MATCH(B56,$K$24:$K$43,0)) | E56: =INDEX($I$24:$I$43,MATCH(B56,$K$24:$K$43,0))
B57: =ROWS($B$48:B57) | C57: =INDEX($B$24:$B$43,MATCH(B57,$K$24:$K$43,0)) | D57: =INDEX($H$24:$H$43,MATCH(B57,$K$24:$K$43,0)) | E57: =INDEX($I$24:$I$43,MATCH(B57,$K$24:$K$43,0))
B59: Two-way: NPV (EURm) - rows: Pillar C: peak uplift in average ticket; columns: Contribution margin on incremental revenue
D60: Columns: Contribution margin on incremental revenue
C61: =Calculations!$E$172 | D61: =Inputs!$E$35+(Inputs!$G$35-Inputs!$E$35)*(COLUMNS($D$61:D61)-1)/(COLUMNS($D$61:$H$61)-1) | E61: =Inputs!$E$35+(Inputs!$G$35-Inputs!$E$35)*(COLUMNS($D$61:E61)-1)/(COLUMNS($D$61:$H$61)-1) | F61: =Inputs!$E$35+(Inputs!$G$35-Inputs!$E$35)*(COLUMNS($D$61:F61)-1)/(COLUMNS($D$61:$H$61)-1) | G61: =Inputs!$E$35+(Inputs!$G$35-Inputs!$E$35)*(COLUMNS($D$61:G61)-1)/(COLUMNS($D$61:$H$61)-1) | H61: =Inputs!$E$35+(Inputs!$G$35-Inputs!$E$35)*(COLUMNS($D$61:H61)-1)/(COLUMNS($D$61:$H$61)-1)
B62: Rows: Pillar C: peak uplift in average ticket | C62: =Inputs!$E$27+(Inputs!$G$27-Inputs!$E$27)*(ROWS($C$62:C62)-1)/(ROWS($C$62:$C$66)-1)
C63: =Inputs!$E$27+(Inputs!$G$27-Inputs!$E$27)*(ROWS($C$62:C63)-1)/(ROWS($C$62:$C$66)-1)
C64: =Inputs!$E$27+(Inputs!$G$27-Inputs!$E$27)*(ROWS($C$62:C64)-1)/(ROWS($C$62:$C$66)-1)
C65: =Inputs!$E$27+(Inputs!$G$27-Inputs!$E$27)*(ROWS($C$62:C65)-1)/(ROWS($C$62:$C$66)-1)
C66: =Inputs!$E$27+(Inputs!$G$27-Inputs!$E$27)*(ROWS($C$62:C66)-1)/(ROWS($C$62:$C$66)-1)
B69: Two-way: NPV (EURm) - rows: Terminal growth of incremental FCF after the horizon; columns: Bass p
D70: Columns: Bass p
C71: =Calculations!$E$172 | D71: =Inputs!$E$20+(Inputs!$G$20-Inputs!$E$20)*(COLUMNS($D$71:D71)-1)/(COLUMNS($D$71:$H$71)-1) | E71: =Inputs!$E$20+(Inputs!$G$20-Inputs!$E$20)*(COLUMNS($D$71:E71)-1)/(COLUMNS($D$71:$H$71)-1) | F71: =Inputs!$E$20+(Inputs!$G$20-Inputs!$E$20)*(COLUMNS($D$71:F71)-1)/(COLUMNS($D$71:$H$71)-1) | G71: =Inputs!$E$20+(Inputs!$G$20-Inputs!$E$20)*(COLUMNS($D$71:G71)-1)/(COLUMNS($D$71:$H$71)-1) | H71: =Inputs!$E$20+(Inputs!$G$20-Inputs!$E$20)*(COLUMNS($D$71:H71)-1)/(COLUMNS($D$71:$H$71)-1)
B72: Rows: Terminal growth of incremental FCF after the horizon | C72: =Inputs!$E$42+(Inputs!$G$42-Inputs!$E$42)*(ROWS($C$72:C72)-1)/(ROWS($C$72:$C$76)-1)
C73: =Inputs!$E$42+(Inputs!$G$42-Inputs!$E$42)*(ROWS($C$72:C73)-1)/(ROWS($C$72:$C$76)-1)
C74: =Inputs!$E$42+(Inputs!$G$42-Inputs!$E$42)*(ROWS($C$72:C74)-1)/(ROWS($C$72:$C$76)-1)
C75: =Inputs!$E$42+(Inputs!$G$42-Inputs!$E$42)*(ROWS($C$72:C75)-1)/(ROWS($C$72:$C$76)-1)
C76: =Inputs!$E$42+(Inputs!$G$42-Inputs!$E$42)*(ROWS($C$72:C76)-1)/(ROWS($C$72:$C$76)-1)

Sheet Checks
B1: Checks
B2: Each check reads OK or ERROR. Total errors must be 0 before handover. Then run scripts/check_model.py (the independent judge).
B3: Period | G3: =Calculations!G3 | H3: =Calculations!H3 | I3: =Calculations!I3 | J3: =Calculations!J3 | K3: =Calculations!K3 | L3: =Calculations!L3 | M3: =Calculations!M3 | N3: =Calculations!N3 | ... P3: =Calculations!P3
B4: Year | G4: =Calculations!G4 | H4: =Calculations!H4 | I4: =Calculations!I4 | J4: =Calculations!J4 | K4: =Calculations!K4 | L4: =Calculations!L4 | M4: =Calculations!M4 | N4: =Calculations!N4 | ... P4: =Calculations!P4
B6: Total errors (must be 0) | E6: =COUNTIF(E9:E39,"ERROR")
B8: Check | C8: Value | D8: Limit | E8: Result
B9: Baseline calibration: model base-year revenue vs reported (2024) | C9: =ABS(Calculations!$E$190/Calculations!$E$191-1) | D9: =Inputs!$F$48 | E9: =IF(C9<=D9,"OK","ERROR")
B10: Initiatives add up to stream incremental revenue (abs. difference) | C10: =MAX(L10:P10) | D10: =Inputs!$F$49 | E10: =IF(C10<=D10,"OK","ERROR") | L10: =ABS(Calculations!L128-Calculations!L119) | M10: =ABS(Calculations!M128-Calculations!M119) | N10: =ABS(Calculations!N128-Calculations!N119) | O10: =ABS(Calculations!O128-Calculations!O119) | P10: =ABS(Calculations!P128-Calculations!P119)
B11: Initiatives' EBIT adds up to incremental EBIT (abs. difference) | C11: =MAX(L11:P11) | D11: =Inputs!$F$49 | E11: =IF(C11<=D11,"OK","ERROR") | L11: =ABS(Calculations!L156-Calculations!L160) | M11: =ABS(Calculations!M156-Calculations!M160) | N11: =ABS(Calculations!N156-Calculations!N160) | O11: =ABS(Calculations!O156-Calculations!O160) | P11: =ABS(Calculations!P156-Calculations!P160)
B12: Pillars add up to initiatives (abs. difference) | C12: =MAX(L12:P12) | D12: =Inputs!$F$49 | E12: =IF(C12<=D12,"OK","ERROR") | L12: =ABS(Calculations!L134-Calculations!L128) | M12: =ABS(Calculations!M134-Calculations!M128) | N12: =ABS(Calculations!N134-Calculations!N128) | O12: =ABS(Calculations!O134-Calculations!O128) | P12: =ABS(Calculations!P134-Calculations!P128)
B13: Target = baseline + incremental (abs. difference) | C13: =MAX(L13:P13) | D13: =Inputs!$F$49 | E13: =IF(C13<=D13,"OK","ERROR") | L13: =ABS(Calculations!L118-Calculations!L117-Calculations!L119) | M13: =ABS(Calculations!M118-Calculations!M117-Calculations!M119) | N13: =ABS(Calculations!N118-Calculations!N117-Calculations!N119) | O13: =ABS(Calculations!O118-Calculations!O117-Calculations!O119) | P13: =ABS(Calculations!P118-Calculations!P117-Calculations!P119)
B14: Base case vs history: baseline revenue CAGR inside the historical band (Calculations 9b) | C14: =Calculations!$E$194 | D14: =Calculations!$E$196 | E14: =IF(AND(C14>=Calculations!$E$195,C14<=D14),"OK","ERROR")
B15: Bridge closes: baseline + steps = target (abs. difference) | C15: =ABS(Bridge!C5+SUM(Bridge!C6:C8)-Bridge!C9) | D15: =Inputs!$F$49 | E15: =IF(C15<=D15,"OK","ERROR")
B16: EBIT bridge closes: steps = incremental EBIT (abs. difference) | C16: =ABS(Bridge!C12+SUM(Bridge!C13:C15)-Bridge!C16) | D16: =Inputs!$F$49 | E16: =IF(C16<=D16,"OK","ERROR")
B17: Objectives: strategies add up to the change in Revenue | C17: =ABS(Objectives!D14-Calculations!$E$211) | D17: =Inputs!$F$49 | E17: =IF(C17<=D17,"OK","ERROR")
B18: Objectives: pillars add up to the change in Revenue | C18: =ABS(Objectives!D21-Calculations!$E$211) | D18: =Inputs!$F$49 | E18: =IF(C18<=D18,"OK","ERROR")
B19: Objectives: strategies add up to the change in EBITDA | C19: =ABS(Objectives!E14-Calculations!$E$215) | D19: =Inputs!$F$49 | E19: =IF(C19<=D19,"OK","ERROR")
B20: Objectives: pillars add up to the change in EBITDA | C20: =ABS(Objectives!E21-Calculations!$E$215) | D20: =Inputs!$F$49 | E20: =IF(C20<=D20,"OK","ERROR")
B21: Frameworks: '1. Triple bottom line (Elkington)' adds up to the change in Revenue | C21: =ABS(Frameworks!D10-Calculations!$E$211) | D21: =Inputs!$F$49 | E21: =IF(C21<=D21,"OK","ERROR")
B22: Frameworks: '1. Triple bottom line (Elkington)' adds up to the change in EBITDA | C22: =ABS(Frameworks!E10-Calculations!$E$215) | D22: =Inputs!$F$49 | E22: =IF(C22<=D22,"OK","ERROR")
B23: Frameworks: '3. Ansoff matrix' adds up to the change in Revenue | C23: =ABS(Frameworks!D32-Calculations!$E$211) | D23: =Inputs!$F$49 | E23: =IF(C23<=D23,"OK","ERROR")
B24: Frameworks: '3. Ansoff matrix' adds up to the change in EBITDA | C24: =ABS(Frameworks!E32-Calculations!$E$215) | D24: =Inputs!$F$49 | E24: =IF(C24<=D24,"OK","ERROR")
B25: Frameworks: '4. Marketing mix (4Ps)' adds up to the change in Revenue | C25: =ABS(Frameworks!D44-Calculations!$E$211) | D25: =Inputs!$F$49 | E25: =IF(C25<=D25,"OK","ERROR")
B26: Frameworks: '4. Marketing mix (4Ps)' adds up to the change in EBITDA | C26: =ABS(Frameworks!E44-Calculations!$E$215) | D26: =Inputs!$F$49 | E26: =IF(C26<=D26,"OK","ERROR")
B27: Frameworks: '5. Value chain (Porter)' adds up to the change in Revenue | C27: =ABS(Frameworks!D60-Calculations!$E$211) | D27: =Inputs!$F$49 | E27: =IF(C27<=D27,"OK","ERROR")
B28: Frameworks: '5. Value chain (Porter)' adds up to the change in EBITDA | C28: =ABS(Frameworks!E60-Calculations!$E$215) | D28: =Inputs!$F$49 | E28: =IF(C28<=D28,"OK","ERROR")
B29: Frameworks: profitability tree adds up to the change in EBITDA | C29: =ABS(Frameworks!C21-Calculations!$E$215) | D29: =Inputs!$F$49 | E29: =IF(C29<=D29,"OK","ERROR")
B30: Penetration never exceeds 100% of the addressable market | C30: =MAX(Calculations!K85:P85) | D30: <= 100% | E30: =IF(C30<=1,"OK","ERROR")
B31: No driver goes negative | C31: =MIN(Calculations!K83:P83,Calculations!K93:P93,Calculations!K101:P101) | D31: >= 0 | E31: =IF(C31>=0,"OK","ERROR")
B32: Register: low <= base <= high on every row (count of breaks) | C32: =SUMPRODUCT((Inputs!E6:E53>Inputs!F6:F53)*1)+SUMPRODUCT((Inputs!F6:F53>Inputs!G6:G53)*1) | D32: 0 | E32: =IF(C32=0,"OK","ERROR")
B33: Register: every input has a source and a grade (count missing) | C33: =SUMPRODUCT((Inputs!F6:F53<>"")*(Inputs!I6:I53=""))+SUMPRODUCT((Inputs!F6:F53<>"")*(Inputs!L6:L53="")) | D33: 0 | E33: =IF(C33=0,"OK","ERROR")
B34: Register: uplifts above the reference-class upper quartile have a written justification (count missing) | C34: =SUMPRODUCT((Inputs!D6:D53="uplift")*(Inputs!F6:F53>Inputs!O6:O53)*(Inputs!Q6:Q53="")) | D34: 0 | E34: =IF(C34=0,"OK","ERROR")
B35: Initiative NPVs add up to the strategy NPV (abs. difference) | C35: =ABS(Calculations!$E$186-Calculations!$E$172) | D35: =Inputs!$F$49 | E35: =IF(C35<=D35,"OK","ERROR")
B36: WACC above terminal growth (Gordon model valid) | C36: =Calculations!$E$74-Calculations!$E$65 | D36: > 0 | E36: =IF(C36>0,"OK","ERROR")
B37: Scenarios ordered: NPV low <= base <= high | C37: =IF(AND(Sensitivity!$D$16<=Sensitivity!$D$17,Sensitivity!$D$17<=Sensitivity!$D$18),0,1) | D37: 0 | E37: =IF(C37=0,"OK","ERROR")
B38: Controls neutral: scenario = Base, tornado off, no overrides (count set) | C38: =(Sensitivity!$E$5<>Sensitivity!$C$17)*1+(Sensitivity!$E$6<>0)*1+COUNT(Sensitivity!$E$7)+COUNT(Sensitivity!$E$8)+COUNT(Sensitivity!$E$9)+COUNT(Sensitivity!$E$10) | D38: 0 | E38: =IF(C38=0,"OK","ERROR")
B39: Max YoY growth of target revenue (must stay under the growth cap) | C39: =MAX(L39:P39) | D39: =Inputs!$F$47 | E39: =IF(C39<=D39,"OK","ERROR") | L39: =Calculations!L118/Calculations!K118-1 | M39: =Calculations!M118/Calculations!L118-1 | N39: =Calculations!N118/Calculations!M118-1 | O39: =Calculations!O118/Calculations!N118-1 | P39: =Calculations!P118/Calculations!O118-1

Sheet Driver tree
B1: Driver tree
B2: Every leaf is measurable and has one owning initiative or an explicit split rule.
B4: Target metric: incremental revenue growth (EURm), 2025-2029 vs do-nothing
B5: Revenue stream: Core revenue = Customers x Purchases per customer x Average ticket x Unit conversion: EUR to EURm with customers in millions
B6: Leaf: Customers [m] - owner: Initiative A1 - split: single owner - measured by: History: last reported value of Customers (reported) 2020-2024 (live link to the Actuals sheet). Data: ILLUSTRATIVE - replace (annual report KPIs / case pack)
B7: Initiative: Initiative A1 (a) - Raise customers
B8: Leaf: Purchases per customer [x] - owner: Initiative B1 - split: single owner - measured by: ILLUSTRATIVE - replace (loyalty data)
B9: Initiative: Initiative B1 (b) - Raise purchase frequency
B10: Leaf: Average ticket [EUR] - owner: Initiative C1 - split: single owner - measured by: Derived: revenue / (customers x purchases)
B11: Initiative: Initiative C1 (c) - Raise average ticket
B12: Costs: initiative opex and capex (quantity x unit cost where given); incremental EBIT = incremental revenue x margin + cost savings - opex
B13: Cash: FCF = EBIT x (1 - tax) - capex, discounted at WACC = E/V x (rf + beta x ERP + CRP) + D/V x kd x (1 - tax)

Sheet Data requests
B1: Data Request Sheet
B2: Pull each licensed item from the IE library, export with the exact file name, upload it, and Claude updates the Inputs row.
A4: Who | B4: Needed for (input) | C4: Database / source | D4: Exact table, report or URL | E4: Filters | F4: Years | G4: Export as (file name) | H4: Owner | I4: Status | J4: Route | K4: Manual fallback
A5: Team pulls (IE library) | B5: rev - Revenue (reported) | C5: SABI | D5: Company > Cuentas > Cuenta de perdidas y ganancias | E5: Individual, EUR thousands | F5: 2020-2024 | G5: sabi_example_pl_2020_2024.xlsx | I5: open | J5: Browser agent (supervised), else team manual export | K5: Log in to SABI through the IE library portal, apply the filters, export as sabi_example_pl_2020_2024.xlsx, upload it; until then the provisional value stays (see grade)
